explainaboard/__init__.py
explainaboard/config.py
explainaboard/constants.py
explainaboard/explainaboard_main.py
explainaboard/info.py
explainaboard/info_test.py
explainaboard/table_schema.py
explainaboard/analysis/__init__.py
explainaboard/analysis/analyses.py
explainaboard/analysis/analyses_test.py
explainaboard/analysis/bucketing.py
explainaboard/analysis/bucketing_test.py
explainaboard/analysis/case.py
explainaboard/analysis/case_test.py
explainaboard/analysis/feature.py
explainaboard/analysis/feature_funcs.py
explainaboard/analysis/feature_funcs_test.py
explainaboard/analysis/feature_test.py
explainaboard/analysis/performance.py
explainaboard/analysis/performance_test.py
explainaboard/analysis/result.py
explainaboard/analysis/result_test.py
explainaboard/analysis/sum_attribute.py
explainaboard/loaders/__init__.py
explainaboard/loaders/argument_pair_extraction.py
explainaboard/loaders/argument_pair_extraction_test.py
explainaboard/loaders/aspect_based_sentiment_classification.py
explainaboard/loaders/aspect_based_sentiment_classification_test.py
explainaboard/loaders/cloze_generative.py
explainaboard/loaders/cloze_generative_test.py
explainaboard/loaders/cloze_multiple_choice.py
explainaboard/loaders/cloze_multiple_choice_test.py
explainaboard/loaders/conditional_generation.py
explainaboard/loaders/conditional_generation_test.py
explainaboard/loaders/file_loader.py
explainaboard/loaders/file_loader_test.py
explainaboard/loaders/grammatical_error_correction.py
explainaboard/loaders/grammatical_error_correction_test.py
explainaboard/loaders/kg_link_tail_prediction.py
explainaboard/loaders/kg_link_tail_prediction_test.py
explainaboard/loaders/language_modeling.py
explainaboard/loaders/language_modeling_test.py
explainaboard/loaders/loader.py
explainaboard/loaders/loader_factory.py
explainaboard/loaders/loader_factory_test.py
explainaboard/loaders/meta_evaluation_nlg.py
explainaboard/loaders/qa_extractive.py
explainaboard/loaders/qa_extractive_test.py
explainaboard-0.12.7.dist-info/LICENSE
explainaboard-0.12.7.dist-info/METADATA
explainaboard-0.12.7.dist-info/WHEEL
explainaboard-0.12.7.dist-info/entry_points.txt
explainaboard-0.12.7.dist-info/top_level.txt
explainaboard-0.12.7.dist-info/RECORD
