Metadata-Version: 2.1
Name: explainaboard
Version: 0.12.7
Summary: Explainable Leaderboards for Natural Language Processing
Home-page: https://github.com/neulab/ExplainaBoard
Author: Pengfei Liu
License: MIT License
Platform: UNKNOWN
Classifier: Intended Audience :: Developers
Classifier: Topic :: Text Processing
Classifier: Topic :: Scientific/Engineering :: Artificial Intelligence
Classifier: License :: OSI Approved :: MIT License
Classifier: Programming Language :: Python :: 3.9
Classifier: Programming Language :: Python :: 3.10
Classifier: Programming Language :: Python :: 3 :: Only
License-File: LICENSE
Requires-Dist: datalabs (>=0.4.9)
Requires-Dist: eaas (>=0.3.9)
Requires-Dist: lexicalrichness (!=0.1.6)
Requires-Dist: matplotlib
Requires-Dist: nltk (>=3.2)
Requires-Dist: numpy
Requires-Dist: sacrebleu
Requires-Dist: scikit-learn
Requires-Dist: scipy (~=1.9.2)
Requires-Dist: seqeval
Requires-Dist: spacy
Requires-Dist: tqdm
Requires-Dist: wheel
Requires-Dist: pysqlite3
Requires-Dist: sqlparse (>=0.4.2)
Provides-Extra: dev
Requires-Dist: pre-commit ; extra == 'dev'
